<?xml version="1.0" encoding="UTF-8"?>
<LanguageData>
  
  <!-- EN: attacked member -->
  <AttackedMember.label>anggota diserang</AttackedMember.label>
  
  <!-- EN: guilty prisoner died -->
  <GuiltyPrisonerDied.label>tahanan bersalah meninggal</GuiltyPrisonerDied.label>
  
  <!-- EN: innocent prisoner died -->
  <InnocentPrisonerDied.label>tahanan tidak bersalah meninggal</InnocentPrisonerDied.label>
  
  <!-- EN: member captured -->
  <MemberCaptured.label>anggota ditangkap</MemberCaptured.label>
  
  <!-- EN: member crushed -->
  <MemberCrushed.label>anggota hancur</MemberCrushed.label>
  
  <!-- EN: member exited map healthy -->
  <MemberExitedMapHealthy.label>anggota sehat keluar dari peta</MemberExitedMapHealthy.label>
  
  <!-- EN: member killed -->
  <MemberKilled.label>anggota terbunuh</MemberKilled.label>
  
  <!-- EN: member died -->
  <MemberNeutrallyDied.label>anggota mati</MemberNeutrallyDied.label>
  
  <!-- EN: member sold -->
  <MemberSold.label>anggota terjual</MemberSold.label>
  
  <!-- EN: member stripped -->
  <MemberStripped.label>anggota dilucuti</MemberStripped.label>
  
  <!-- EN: harmful surgery on member -->
  <PerformedHarmfulSurgery.label>operasi berbahaya pada anggota</PerformedHarmfulSurgery.label>
  
  <!-- EN: prisoner died -->
  <PrisonerDied.label>tahanan mati</PrisonerDied.label>
  
  <!-- EN: harmed member -->
  <UsedHarmfulItem.label>anggota berbahaya</UsedHarmfulItem.label>
  
</LanguageData>